[
  {
    "campaignId": 1058,
    "date": "Wed Jun 15 05:00:02 GMT 2016",
    "impressions": 570,
    "clicks": 15,
    "orders": 0,
    "cpm": 2.4,
    "cpc": 0.09,
    "cpo": 0,
    "ctr": 2.63,
    "cvr": 0,
    "orderValue": 0,
    "spend": 0.38,
    "margin": 0,
    "roi": 1
  },
  {
    "campaignId": 1057,
    "date": "Wed Jun 15 05:00:02 GMT 2016",
    "impressions": 160556,
    "clicks": 1051,
    "orders": 0,
    "cpm": 0.89,
    "cpc": 0.14,
    "cpo": 0,
    "ctr": 0.65,
    "cvr": 0,
    "orderValue": 0,
    "spend": 107.57,
    "margin": 0,
    "roi": 1
  },
  {
    "campaignId": 1217,
    "date": "Wed Jun 15 05:00:02 GMT 2016",
    "impressions": 150312,
    "clicks": 1305,
    "orders": 0,
    "cpm": 1.96,
    "cpc": 0.23,
    "cpo": 0,
    "ctr": 0.87,
    "cvr": 0,
    "orderValue": 0,
    "spend": 0,
    "margin": 0,
    "roi": 1
  },
  {
    "campaignId": 1058,
    "date": "Thu Jun 16 05:00:01 GMT 2016",
    "impressions": 659,
    "clicks": 22,
    "orders": 0,
    "cpm": 2.41,
    "cpc": 0.07,
    "cpo": 0,
    "ctr": 3.34,
    "cvr": 0,
    "orderValue": 0,
    "spend": 0.44,
    "margin": 0,
    "roi": 1
  },
  {
    "campaignId": 1057,
    "date": "Thu Jun 16 05:00:01 GMT 2016",
    "impressions": 160499,
    "clicks": 905,
    "orders": 0,
    "cpm": 0.85,
    "cpc": 0.15,
    "cpo": 0,
    "ctr": 0.56,
    "cvr": 0,
    "orderValue": 0,
    "spend": 107.53,
    "margin": 0,
    "roi": 1
  },
  {
    "campaignId": 1217,
    "date": "Thu Jun 16 05:00:01 GMT 2016",
    "impressions": 150659,
    "clicks": 1079,
    "orders": 0,
    "cpm": 2.04,
    "cpc": 0.29,
    "cpo": 0,
    "ctr": 0.72,
    "cvr": 0,
    "orderValue": 0,
    "spend": 0,
    "margin": 0,
    "roi": 1
  },
  {
    "campaignId": 1058,
    "date": "Fri Jun 17 05:00:01 GMT 2016",
    "impressions": 563,
    "clicks": 22,
    "orders": 0,
    "cpm": 2.36,
    "cpc": 0.06,
    "cpo": 0,
    "ctr": 3.91,
    "cvr": 0,
    "orderValue": 0,
    "spend": 0.38,
    "margin": 0,
    "roi": 1
  },
  {
    "campaignId": 1057,
    "date": "Fri Jun 17 05:00:01 GMT 2016",
    "impressions": 160153,
    "clicks": 1221,
    "orders": 0,
    "cpm": 0.8,
    "cpc": 0.11,
    "cpo": 0,
    "ctr": 0.76,
    "cvr": 0,
    "orderValue": 0,
    "spend": 107.3,
    "margin": 0,
    "roi": 1
  },
  {
    "campaignId": 1217,
    "date": "Fri Jun 17 05:00:01 GMT 2016",
    "impressions": 150144,
    "clicks": 1335,
    "orders": 0,
    "cpm": 1.96,
    "cpc": 0.22,
    "cpo": 0,
    "ctr": 0.89,
    "cvr": 0,
    "orderValue": 0,
    "spend": 0,
    "margin": 0,
    "roi": 1
  },
  {
    "campaignId": 1058,
    "date": "Sat Jun 18 05:00:02 GMT 2016",
    "impressions": 751,
    "clicks": 27,
    "orders": 0,
    "cpm": 2.55,
    "cpc": 0.07,
    "cpo": 0,
    "ctr": 3.6,
    "cvr": 0,
    "orderValue": 0,
    "spend": 0.5,
    "margin": 0,
    "roi": 1
  },
  {
    "campaignId": 1057,
    "date": "Sat Jun 18 05:00:02 GMT 2016",
    "impressions": 160186,
    "clicks": 1813,
    "orders": 0,
    "cpm": 0.91,
    "cpc": 0.08,
    "cpo": 0,
    "ctr": 1.13,
    "cvr": 0,
    "orderValue": 0,
    "spend": 107.32,
    "margin": 0,
    "roi": 1
  },
  {
    "campaignId": 1217,
    "date": "Sat Jun 18 05:00:02 GMT 2016",
    "impressions": 150197,
    "clicks": 1433,
    "orders": 0,
    "cpm": 1.94,
    "cpc": 0.2,
    "cpo": 0,
    "ctr": 0.95,
    "cvr": 0,
    "orderValue": 0,
    "spend": 0,
    "margin": 0,
    "roi": 1
  },
  {
    "campaignId": 1058,
    "date": "Sun Jun 19 05:00:02 GMT 2016",
    "impressions": 725,
    "clicks": 39,
    "orders": 0,
    "cpm": 2.38,
    "cpc": 0.04,
    "cpo": 0,
    "ctr": 5.38,
    "cvr": 0,
    "orderValue": 0,
    "spend": 0.49,
    "margin": 0,
    "roi": 1
  },
  {
    "campaignId": 1057,
    "date": "Sun Jun 19 05:00:02 GMT 2016",
    "impressions": 160588,
    "clicks": 1174,
    "orders": 0,
    "cpm": 0.98,
    "cpc": 0.13,
    "cpo": 0,
    "ctr": 0.73,
    "cvr": 0,
    "orderValue": 0,
    "spend": 107.59,
    "margin": 0,
    "roi": 1
  },
  {
    "campaignId": 1217,
    "date": "Sun Jun 19 05:00:02 GMT 2016",
    "impressions": 134565,
    "clicks": 1014,
    "orders": 0,
    "cpm": 2.01,
    "cpc": 0.27,
    "cpo": 0,
    "ctr": 0.75,
    "cvr": 0,
    "orderValue": 0,
    "spend": 0,
    "margin": 0,
    "roi": 1
  },
  {
    "campaignId": 1058,
    "date": "Mon Jun 20 05:00:01 GMT 2016",
    "impressions": 711,
    "clicks": 33,
    "orders": 0,
    "cpm": 2.28,
    "cpc": 0.05,
    "cpo": 0,
    "ctr": 4.64,
    "cvr": 0,
    "orderValue": 0,
    "spend": 0.48,
    "margin": 0,
    "roi": 1
  },
  {
    "campaignId": 1057,
    "date": "Mon Jun 20 05:00:01 GMT 2016",
    "impressions": 160262,
    "clicks": 1091,
    "orders": 0,
    "cpm": 0.8,
    "cpc": 0.12,
    "cpo": 0,
    "ctr": 0.68,
    "cvr": 0,
    "orderValue": 0,
    "spend": 107.38,
    "margin": 0,
    "roi": 1
  },
  {
    "campaignId": 1217,
    "date": "Mon Jun 20 05:00:01 GMT 2016",
    "impressions": 100162,
    "clicks": 701,
    "orders": 0,
    "cpm": 2.19,
    "cpc": 0.31,
    "cpo": 0,
    "ctr": 0.7,
    "cvr": 0,
    "orderValue": 0,
    "spend": 0,
    "margin": 0,
    "roi": 1
  },
  {
    "campaignId": 1058,
    "date": "Tue Jun 21 05:00:01 GMT 2016",
    "impressions": 711,
    "clicks": 33,
    "orders": 0,
    "cpm": 2.28,
    "cpc": 0.05,
    "cpo": 0,
    "ctr": 4.64,
    "cvr": 0,
    "orderValue": 0,
    "spend": 0.48,
    "margin": 0,
    "roi": 1
  },
  {
    "campaignId": 1057,
    "date": "Tue Jun 21 05:00:01 GMT 2016",
    "impressions": 160262,
    "clicks": 1091,
    "orders": 0,
    "cpm": 0.8,
    "cpc": 0.12,
    "cpo": 0,
    "ctr": 0.68,
    "cvr": 0,
    "orderValue": 0,
    "spend": 107.38,
    "margin": 0,
    "roi": 1
  },
  {
    "campaignId": 1217,
    "date": "Tue Jun 21 05:00:01 GMT 2016",
    "impressions": 100162,
    "clicks": 703,
    "orders": 0,
    "cpm": 2.19,
    "cpc": 0.31,
    "cpo": 0,
    "ctr": 0.7,
    "cvr": 0,
    "orderValue": 0,
    "spend": 0,
    "margin": 0,
    "roi": 1
  }
]